listxml.py
listxml-0.5.0.dist-info/METADATA
listxml-0.5.0.dist-info/WHEEL
listxml-0.5.0.dist-info/licenses/LICENCE.txt
listxml-0.5.0.dist-info/RECORD
