Metadata-Version: 2.4
Name: listxml
Version: 0.5.0
Summary: An _unpythonic_ XML writer (and reader)!
Project-URL: repository, https://heptapod.host/nxg/listxml
Author-email: Norman Gray <gray@nxg.name>
License: BSD License (2-clause)
License-File: LICENCE.txt
Classifier: Development Status :: 4 - Beta
Classifier: Intended Audience :: Developers
Classifier: License :: OSI Approved :: BSD License
Classifier: Operating System :: OS Independent
Classifier: Programming Language :: Python :: 3
Classifier: Topic :: Text Processing :: Markup :: XML
Requires-Python: >=3.0
